IM_COOL_BOOY_GIF/__init__.py
IM_COOL_BOOY_GIF/coolbooyhelp_text.py
IM_COOL_BOOY_GIF/init.py
IM_COOL_BOOY_GIF/main.py
im_cool_booy_gif-1.2.2.dist-info/licenses/LICENSE
im_cool_booy_gif-1.2.2.dist-info/METADATA
im_cool_booy_gif-1.2.2.dist-info/WHEEL
im_cool_booy_gif-1.2.2.dist-info/entry_points.txt
im_cool_booy_gif-1.2.2.dist-info/top_level.txt
im_cool_booy_gif-1.2.2.dist-info/RECORD
