Metadata-Version: 2.4
Name: IM-COOL-BOOY-GIF
Version: 1.2.2
Summary: A Cool Command-Line GIF Tool by COOL BOOY. This is a simple yet powerful tool designed to work seamlessly through the command line, allowing users to generate and manage GIFs easily. Whether you're looking to create GIFs from videos or manipulate them in various ways, this tool offers a straightforward interface for all your GIF-related needs.
Author: coolbooy
Author-email: coolbooy@gmail.com
License: MIT
Keywords: gif,image,hd,tool
Classifier: Programming Language :: Python :: 3.12
Classifier: Operating System :: OS Independent
Requires-Python: >=3.6
License-File: LICENSE
Requires-Dist: Pillow
Requires-Dist: imageio
Requires-Dist: numpy
Requires-Dist: tqdm
Dynamic: author
Dynamic: author-email
Dynamic: classifier
Dynamic: description
Dynamic: description-content-type
Dynamic: keywords
Dynamic: license
Dynamic: license-file
Dynamic: requires-dist
Dynamic: requires-python
Dynamic: summary
